apputils/__init__.py
apputils/_constants.py
apputils/_file_lock.py
apputils/_import/__init__.py
apputils/appdata.py
apputils/tools.py
apputils/type_tools.py
bblogger/__init__.py
bblogger/_constants.py
bblogger/_data/LICENSE-hljs
bblogger/_data/LICENSE-ofl
bblogger/_data/SpaceMono-Bold.ttf
bblogger/_data/SpaceMono-BoldItalic.ttf
bblogger/_data/SpaceMono-Italic.ttf
bblogger/_data/SpaceMono-Regular.ttf
bblogger/_data/__init__.py
bblogger/_data/arta.css
bblogger/_data/default.css
bblogger/_data/highlight/LICENSE
bblogger/_data/highlight.min.js
bblogger/_data/new_html
texttools/.__init__.py.kate-swp
texttools/__init__.py
texttools/_ansi_data.py
texttools/_cache.py
texttools/_constants.py
texttools/_data/16colors.json
texttools/_data/__init__.py
texttools/_data/colors.json
texttools/_data/styles.json
texttools/_data/user_color_template.json
texttools/_esc_ext.py
texttools/_type_functions.py
texttools/ansitools.py
texttools/color_mods.py
texttools/cursorcontrols.py
texttools/escapes.py
texttools/texttools.py
texttools/types.py
bb_apputils-0.5.3.dist-info/METADATA
bb_apputils-0.5.3.dist-info/WHEEL
bb_apputils-0.5.3.dist-info/entry_points.txt
bb_apputils-0.5.3.dist-info/RECORD
