Metadata-Version: 2.1
Name: BB_AppUtils
Version: 0.5.3
Summary: Python development tools
Author: Erik Beebe
Author-email: beebeapps_debugging@tuta.io
Requires-Python: >=3.11,<4.0
Classifier: Programming Language :: Python :: 3
Classifier: Programming Language :: Python :: 3.11
Classifier: Programming Language :: Python :: 3.12
Requires-Dist: bb-pycodeview (>=0.1.2,<0.2.0)
Requires-Dist: dateutils (>=0.6.12,<0.7.0)
